tc_gcs/__init__.py
tc_gcs/gcs/__init__.py
tc_gcs/gcs/bucket.py
tc_gcs/gcs/storage.py
tc_gcs/storages/__init__.py
tc_gcs/storages/gcs_storage.py
tc_gcs-0.1.1.dist-info/LICENSE
tc_gcs-0.1.1.dist-info/METADATA
tc_gcs-0.1.1.dist-info/WHEEL
tc_gcs-0.1.1.dist-info/top_level.txt
tc_gcs-0.1.1.dist-info/RECORD
