Metadata-Version: 2.1
Name: tc-gcs
Version: 0.1.1
Summary: A simple Thumbor custom storage for Google Cloud Storage
Author: Ngo Sach Nhat (Chen)
Author-email: nhatns.uet@gmail.com
License: MIT
Keywords: thumbor gcs google cloud storage
Classifier: Development Status :: 3 - Alpha
Classifier: Intended Audience :: Developers
Classifier: License :: OSI Approved :: MIT License
Classifier: Programming Language :: Python :: 3
Classifier: Operating System :: OS Independent
License-File: LICENSE
Requires-Dist: thumbor >=7.6.0
Requires-Dist: google-cloud-storage >=2.14.0
